[
    {
        "title": "Utazás Haza",
        "type": "attack",
        "quantity": 1
    },
    {
        "title": "Szerencse és a Sors Kegyeltje",
        "type": "attack",
        "quantity": 3
    },
    {
        "title": "Utazás a Bálna-Szigetre",
        "type": "attack",
        "quantity": 1
    },
    {
        "title": "Utazás a Kigyók Völgyébe",
        "type": "attack",
        "quantity": 1
    },
    {
        "title": "Utazás a Tűzszemű Szörnyhöz",
        "type": "attack",
        "quantity": 1
    },
    {
        "title": "Utazás az Őrült Kannibálokhoz",
        "type": "attack",
        "quantity": 1
    },
    {
        "title": "Utazás az Emberevő Majmok Városába",
        "type": "attack",
        "quantity": 1
    },
    {
        "title": "Utazás Szerenbid Király Városába",
        "type": "attack",
        "quantity": 1
    },
    {
        "title": "A Parancs Hatása",
        "type": "attack",
        "quantity": 1
    },
    {
        "title": "Zsákmány",
        "type": "versatile",
        "quantity": 2
    },
    {
        "title": "Küzdelem és Veszély",
        "type": "versatile",
        "quantity": 4
    },
    {
        "title": "Félreugrás",
        "type": "versatile",
        "quantity": 2
    },
    {
        "title": "Lendületes Mozdulat",
        "type": "versatile",
        "quantity": 3
    },
    {
        "title": "Színlelt Támadás",
        "type": "versatile",
        "quantity": 3
    },
    {
        "title": "Újrarendeződés",
        "type": "versatile",
        "quantity": 3
    },
    {
        "title": "Hét Tengerek Kincse",
        "type": "scheme",
        "quantity": 2
    }
]